neurokit/__init__.py
neurokit/bio/__init__.py
neurokit/bio/bio_data.py
neurokit/bio/bio_ecg.py
neurokit/bio/bio_ecg_preprocessing.py
neurokit/bio/bio_eda.py
neurokit/bio/bio_emg.py
neurokit/bio/bio_meta.py
neurokit/bio/bio_rsp.py
neurokit/eeg/__init__.py
neurokit/eeg/eeg_complexity.py
neurokit/eeg/eeg_data.py
neurokit/eeg/eeg_erp.py
neurokit/materials/__init__.py
neurokit/materials/heartbeat_classification.model
neurokit/miscellaneous/__init__.py
neurokit/miscellaneous/data.py
neurokit/miscellaneous/miscellaneous.py
neurokit/signal/__init__.py
neurokit/signal/complexity.py
neurokit/signal/epochs.py
neurokit/signal/events.py
neurokit/signal/signal.py
neurokit/statistics/__init__.py
neurokit/statistics/plot.py
neurokit/statistics/routines.py
neurokit/statistics/statistics.py
neurokit-0.2.0.dist-info/DESCRIPTION.rst
neurokit-0.2.0.dist-info/METADATA
neurokit-0.2.0.dist-info/RECORD
neurokit-0.2.0.dist-info/WHEEL
neurokit-0.2.0.dist-info/metadata.json
neurokit-0.2.0.dist-info/top_level.txt
tests/__init__.py
tests/test_bio.py
tests/test_miscellaneous.py
tests/test_statistics.py
