Metadata-Version: 2.0
Name: neurokit
Version: 0.2.0
Summary: A Python Toolbox for Statistics and Signal Processing (EEG, EDA, ECG, EMG...).
Home-page: https://github.com/neuropsychology/NeuroKit.py
Author: Dominique Makowski
Author-email: dom.makowski@gmail.com
License: MIT
Download-URL: https://github.com/neuropsychology/NeuroKit.py/tarball/master
Keywords: python signal processing EEG EDA ECG hrv rpeaks biosignals complexity
Platform: UNKNOWN
Classifier: Intended Audience :: Science/Research
Classifier: Intended Audience :: Developers
Classifier: Programming Language :: Python
Classifier: Topic :: Software Development
Classifier: Topic :: Scientific/Engineering
Classifier: Operating System :: Microsoft :: Windows
Classifier: Operating System :: Unix
Classifier: Operating System :: MacOS
Classifier: Programming Language :: Python :: 3.5
Classifier: Programming Language :: Python :: 3.6
Requires-Dist: Pillow
Requires-Dist: bioread
Requires-Dist: biosppy
Requires-Dist: cvxopt
Requires-Dist: matplotlib
Requires-Dist: mne
Requires-Dist: nolds
Requires-Dist: numpy
Requires-Dist: pandas
Requires-Dist: scipy
Requires-Dist: sklearn
